echo_lv/__init__.py
echo_lv/__main__.py
echo_lv/import_image_from_video.py
echo_lv/lv.py
echo_lv/lv_other.py
echo_lv/metrics.py
echo_lv/take_contour.py
echo_lv/utils.py
echo_lv/data/__init__.py
echo_lv/data/data_camus.py
echo_lv/data/data_ekb.py
echo_lv/data/other.py
echo_lv-0.1.3.dist-info/LICENSE
echo_lv-0.1.3.dist-info/METADATA
echo_lv-0.1.3.dist-info/WHEEL
echo_lv-0.1.3.dist-info/top_level.txt
echo_lv-0.1.3.dist-info/RECORD
