Metadata-Version: 2.1
Name: echo-lv
Version: 0.1.3
Summary: Library for Echocardiographic images
Home-page: https://github.com/zvvzuzin/us_left_ventricle
Author: Zyuzin Vasily
Author-email: zvvzuzin@gmail.com
License: UNKNOWN
Platform: UNKNOWN
Classifier: Programming Language :: Python :: 3
Classifier: License :: OSI Approved :: MIT License
Classifier: Operating System :: OS Independent
Requires-Dist: SimpleITK
Requires-Dist: matplotlib (>=1.5.1)
Requires-Dist: numpy (>=1.11.1)
Requires-Dist: opencv-python
Requires-Dist: pandas
Requires-Dist: scikit-image
Requires-Dist: scipy
Requires-Dist: torch
